[{"id":"54c83eef-8492-4e6c-94ba-1ca031ebfa58","title":"Sophie books","copy":"sophie.9@live.nl","user":"3","prio":"low","description":"asdfasdf"},{"id":"b2c039d0-9c4b-496a-b530-f15d5a28f5a9","title":"Hello","copy":"sophie.9@live.nl","user":"3","prio":"low","description":"asdfasdf"},{"id":"d1ef42b5-7bef-41b7-a743-7d40fdadb1bc","title":"Hello","copy":"sophie.9@live.nl","user":"3","prio":"low","description":"asdfasdf"},{"id":"c4bd54dc-a16a-47c2-9b02-a86bfe0cc3f0","title":"Sophie books","copy":"sophie.9@live.nl","user":"8","prio":"high"}]